GoogleFreeTrans/CalcTk.py
GoogleFreeTrans/Translator.py
GoogleFreeTrans/__init__.py
GoogleFreeTrans/gettkk.py
GoogleFreeTrans-0.1.3.dist-info/DESCRIPTION.rst
GoogleFreeTrans-0.1.3.dist-info/METADATA
GoogleFreeTrans-0.1.3.dist-info/RECORD
GoogleFreeTrans-0.1.3.dist-info/WHEEL
GoogleFreeTrans-0.1.3.dist-info/metadata.json
GoogleFreeTrans-0.1.3.dist-info/top_level.txt
