Metadata-Version: 2.0
Name: GoogleFreeTrans
Version: 0.1.3
Summary: Free Google Translate API for Python. Translates totally free of charge.
Home-page: https://github.com/ziliwang/GoogleFreeTrans
Author: wangzili
Author-email: wzlnot@gmail.com
License: MIT
Requires-Dist: PyExecJS
Requires-Dist: requests
